{"cameraMode":{"drawMode":0,"name":"Shaded","section":"Shading Mode"},"sceneLighting":true,"audioPlay":false,"sceneViewState":{"m_AlwaysRefresh":false,"showFog":true,"showSkybox":true,"showFlares":true,"showImageEffects":true,"showParticleSystems":true,"showVisualEffectGraphs":true,"m_FxEnabled":true},"in2DMode":false,"pivot":{"x":-0.3508281111717224,"y":1.2548562288284302,"z":0.9825485348701477},"rotation":{"x":0.11009214073419571,"y":0.011594478040933609,"z":-0.0012844305019825698,"w":0.9938446879386902},"size":2.8965394496917726,"orthographic":false}